{
    "model": "xgboost_tuned",
    "best_params": {
        "n_estimators": 200,
        "max_depth": 4,
        "learning_rate": 0.05,
        "subsample": 1.0,
        "colsample_bytree": 0.8
    },
    "metrics": {
        "accuracy": 0.7291039592498263,
        "precision": 0.7578647925033467,
        "recall": 0.6870449029126213,
        "f1_score": 0.7207192870782941
    },
    "top_features": [
        {
            "feature": "ap_hi",
            "importance": 0.4202990233898163
        },
        {
            "feature": "map",
            "importance": 0.1478736400604248
        },
        {
            "feature": "ap_lo",
            "importance": 0.1172582283616066
        },
        {
            "feature": "age_chol_interaction",
            "importance": 0.08715733140707016
        },
        {
            "feature": "cholesterol",
            "importance": 0.054709672927856445
        },
        {
            "feature": "age",
            "importance": 0.03795133903622627
        },
        {
            "feature": "pulse_pressure",
            "importance": 0.034994836896657944
        },
        {
            "feature": "alco",
            "importance": 0.016539622098207474
        },
        {
            "feature": "smoke",
            "importance": 0.015814390033483505
        },
        {
            "feature": "active",
            "importance": 0.015276189893484116
        }
    ]
}